doc23/__init__.py
doc23/allowed_types.py
doc23/config_tree.py
doc23/core.py
doc23/exceptions.py
doc23/gardener.py
doc23/logging.py
doc23/extractors/__init__.py
doc23/extractors/base.py
doc23/extractors/docx.py
doc23/extractors/image.py
doc23/extractors/markdown.py
doc23/extractors/odt.py
doc23/extractors/pdf.py
doc23/extractors/rtf.py
doc23/extractors/text.py
doc23/ocr/__init__.py
doc23/ocr/processor.py
doc23-0.1.2.dist-info/METADATA
doc23-0.1.2.dist-info/WHEEL
doc23-0.1.2.dist-info/top_level.txt
doc23-0.1.2.dist-info/RECORD
