Metadata-Version: 2.4
Name: doc23
Version: 0.1.2
Summary: Powerful Python library to convert documents (PDF, DOCX, TXT) into structured JSON trees for legal, institutional, and NLP applications.
Author: Alex Vargas
License-Expression: MIT
Project-URL: Homepage, https://github.com/alexvargashn/doc23
Project-URL: Documentation, https://github.com/alexvargashn/doc23#readme
Project-URL: Source, https://github.com/alexvargashn/doc23
Project-URL: Bug Tracker, https://github.com/alexvargashn/doc23/issues
Keywords: document parsing,legaltech,NLP,PDF to JSON,text extraction,structure,OCR,AI
Classifier: Programming Language :: Python :: 3
Classifier: Operating System :: OS Independent
Classifier: Topic :: Text Processing
Classifier: Intended Audience :: Developers
Classifier: Development Status :: 3 - Alpha
Requires-Python: >=3.10
Requires-Dist: annotated-types<1.0.0,>=0.7.0
Requires-Dist: anyio<5.0.0,>=4.8.0
Requires-Dist: certifi<2026.0.0,>=2025.1.31
Requires-Dist: cffi<2.0.0,>=1.17.1
Requires-Dist: charset-normalizer<4.0.0,>=3.4.1
Requires-Dist: click<9.0.0,>=8.1.8
Requires-Dist: cryptography<45.0.0,>=44.0.2
Requires-Dist: dnspython<3.0.0,>=2.7.0
Requires-Dist: docx2txt<1.0.0,>=0.8
Requires-Dist: pdf2image<2.0.0,>=1.17.0
Requires-Dist: python-docx<2.0.0,>=1.1.0
Requires-Dist: odfpy<2.0.0,>=1.4.1
Requires-Dist: h11<1.0.0,>=0.14.0
Requires-Dist: httpcore<2.0.0,>=1.0.7
Requires-Dist: httptools<1.0.0,>=0.6.4
Requires-Dist: httpx<0.29.0,>=0.28.1
Requires-Dist: idna<4.0,>=3.10
Requires-Dist: Jinja2<4.0.0,>=3.1.5
Requires-Dist: markdown<4.0.0,>=3.5.2
Requires-Dist: python-magic<1.0.0,>=0.4.27
Requires-Dist: python-multipart<1.0.0,>=0.0.20
Requires-Dist: PyYAML<7.0.0,>=6.0.2
Requires-Dist: sniffio<2.0.0,>=1.3.1
Requires-Dist: striprtf<1.0.0,>=0.0.28
Requires-Dist: typing_extensions<5.0.0,>=4.12.2
Requires-Dist: pdfplumber<1.0.0,>=0.11.5
Requires-Dist: pytesseract<1.0.0,>=0.3.10
Requires-Dist: Pillow<12.0.0,>=11.1.0
